README.md
setup.py
conf/__init__.py
conf/config.py
dingding_client/__init__.py
dingding_client/notice_client.py
inner_lib/__init__.py
inner_lib/func_ext.py
inner_lib/log.py
shopex_dingding_note_2.x.egg-info/PKG-INFO
shopex_dingding_note_2.x.egg-info/SOURCES.txt
shopex_dingding_note_2.x.egg-info/dependency_links.txt
shopex_dingding_note_2.x.egg-info/top_level.txt
test/SendMessageToDingDingTestCase.py
test/__init__.py