Metadata-Version: 2.1
Name: shopex-dingding-note-2.x
Version: 1.4
Summary: ShopEx dingding notify for python
Home-page: https://github.com/magic119/shopex_dingding_note_2.x.git
Author: ShopEx
Author-email: xuhongtao@shopex.cn
License: LGPL
Platform: README.md
Requires-Python: >=2.7.0, <2.7.18
